mcvqoe/intelligibility/__init__.py
mcvqoe/intelligibility/intelligibility.py
mcvqoe/intelligibility/intelligibility_eval.py
mcvqoe/intelligibility/intelligibility_reprocess.py
mcvqoe/intelligibility/intelligibility_simulate.py
mcvqoe/intelligibility/intelligibility_test.py
mcvqoe/intelligibility/version.py
mcvqoe/intelligibility/audio_clips/F1_b10_w1_orig.wav
mcvqoe/intelligibility/audio_clips/F1_b10_w2_orig.wav
mcvqoe/intelligibility/audio_clips/F1_b10_w3_orig.wav
mcvqoe/intelligibility/audio_clips/F1_b10_w4_orig.wav
mcvqoe/intelligibility/audio_clips/F1_b10_w5_orig.wav
mcvqoe/intelligibility/audio_clips/F1_b10_w6_orig.wav
mcvqoe/intelligibility/audio_clips/F1_b11_w1_orig.wav
mcvqoe/intelligibility/audio_clips/F1_b11_w2_orig.wav
mcvqoe/intelligibility/audio_clips/F1_b11_w3_orig.wav
mcvqoe/intelligibility/audio_clips/F1_b11_w4_orig.wav
mcvqoe/intelligibility/audio_clips/F1_b11_w5_orig.wav
mcvqoe/intelligibility/audio_clips/F1_b11_w6_orig.wav
mcvqoe/intelligibility/audio_clips/F1_b12_w1_orig.wav
mcvqoe/intelligibility/audio_clips/F1_b12_w2_orig.wav
mcvqoe/intelligibility/audio_clips/F1_b12_w3_orig.wav
mcvqoe/intelligibility/audio_clips/F1_b12_w4_orig.wav
mcvqoe/intelligibility/audio_clips/F1_b12_w5_orig.wav
mcvqoe/intelligibility/audio_clips/F1_b12_w6_orig.wav
mcvqoe/intelligibility/audio_clips/F1_b13_w1_orig.wav
mcvqoe/intelligibility/audio_clips/F1_b13_w2_orig.wav
mcvqoe/intelligibility/audio_clips/F1_b13_w3_orig.wav
mcvqoe/intelligibility/audio_clips/F1_b13_w4_orig.wav
mcvqoe/intelligibility/audio_clips/F1_b13_w5_orig.wav
mcvqoe/intelligibility/audio_clips/F1_b13_w6_orig.wav
mcvqoe/intelligibility/audio_clips/F1_b14_w1_orig.wav
mcvqoe/intelligibility/audio_clips/F1_b14_w2_orig.wav
mcvqoe/intelligibility/audio_clips/F1_b14_w3_orig.wav
mcvqoe/intelligibility/audio_clips/F1_b14_w4_orig.wav
mcvqoe/intelligibility/audio_clips/F1_b14_w5_orig.wav
mcvqoe/intelligibility/audio_clips/F1_b14_w6_orig.wav
mcvqoe/intelligibility/audio_clips/F1_b15_w1_orig.wav
mcvqoe_intelligibility-1.1.3.dist-info/LICENSE.md
mcvqoe_intelligibility-1.1.3.dist-info/METADATA
mcvqoe_intelligibility-1.1.3.dist-info/WHEEL
mcvqoe_intelligibility-1.1.3.dist-info/entry_points.txt
mcvqoe_intelligibility-1.1.3.dist-info/top_level.txt
mcvqoe_intelligibility-1.1.3.dist-info/RECORD
