Metadata-Version: 2.2
Name: mcvqoe-intelligibility
Version: 1.1.3
Summary: Measurement code for intelligibility
Home-page: https://github.com/usnistgov/intelligibility
Author: PSCR
Author-email: PSCR@PSCR.gov
License: NIST software License
Classifier: Programming Language :: Python :: 3
Classifier: License :: Public Domain
Classifier: Operating System :: OS Independent
Requires-Python: >=3.6
License-File: LICENSE.md
Requires-Dist: mcvqoe-base
Requires-Dist: abcmrt16
Requires-Dist: plotly
Requires-Dist: numpy
Requires-Dist: pandas
Dynamic: author
Dynamic: author-email
Dynamic: classifier
Dynamic: description
Dynamic: description-content-type
Dynamic: home-page
Dynamic: license
Dynamic: requires-dist
Dynamic: requires-python
Dynamic: summary
